Workbook

Sheet Instrucciones
A1: MODELO DE VARIACIONES P&L — MES A MES (Budget vs Actual)
A3: Estructura oficial de grupos (cuadra con vuestro EBITDA y EBT reportados).
A5: CÓMO FUNCIONA
A6: 1) 'Budget': presupuesto por mes. Junio cargado; rellena el resto cuando lo tengas.
A7: 2) 'Actual (ST)': reales. Junio cerrado y cargado. Cada cierre, pega/vincula la columna del mes.
A8: 3) 'Variaciones' y 'Variaciones %': se calculan solas (Actual − Budget). No tocar.
A9: 4) 'Dashboard': resumen visual de junio.
A11: VINCULAR EL FICHERO ST CADA MES
A12: Opción A (recomendada): en 'Actual (ST)', celda del mes, fórmula al fichero ST. Ej:
A13: ='[ST_Junio.xlsx]P&L'!$C$10 (ajusta fichero, hoja y celda de origen)
A14: Opción B: Datos > Obtener datos > Desde un libro, enlazas la tabla del ST.
A15: Opción C: pega los valores del mes (pegado normal).
... A22: Cifras en euros. Budget/Actual junio: hoja 'DiF (BDG March)' del fichero original.

Sheet Budget
A1: BUDGET 2026 — P&L mensual (€)
A3: Concepto | B3: Ene | C3: Feb | D3: Mar | E3: Abr | F3: May | G3: Jun | H3: Jul | I3: Ago | J3: Sep | K3: Oct | L3: Nov | M3: Dic | N3: FY Total
A4: INGRESOS
A5: Passenger Revenue | B5: 0 | C5: 0 | D5: 0 | E5: 0 | F5: 0 | G5: 50518236 | H5: 0 | I5: 0 | J5: 0 | K5: 0 | L5: 0 | M5: 0 | N5: =SUM(B5:M5)
A6: Shuttle | B6: 0 | C6: 0 | D6: 0 | E6: 0 | F6: 0 | G6: 921600 | H6: 0 | I6: 0 | J6: 0 | K6: 0 | L6: 0 | M6: 0 | N6: =SUM(B6:M6)
A7: Charter | B7: 0 | C7: 0 | D7: 0 | E7: 0 | F7: 0 | G7: 0 | H7: 0 | I7: 0 | J7: 0 | K7: 0 | L7: 0 | M7: 0 | N7: =SUM(B7:M7)
A8: Ancillary Revenue | B8: 0 | C8: 0 | D8: 0 | E8: 0 | F8: 0 | G8: 31961512 | H8: 0 | I8: 0 | J8: 0 | K8: 0 | L8: 0 | M8: 0 | N8: =SUM(B8:M8)
A9: Total Revenue | B9: =SUM(B5:B8) | C9: =SUM(C5:C8) | D9: =SUM(D5:D8) | E9: =SUM(E5:E8) | F9: =SUM(F5:F8) | G9: =SUM(G5:G8) | H9: =SUM(H5:H8) | I9: =SUM(I5:I8) | ... M9: =SUM(M5:M8) | N9: =SUM(B9:M9)
A10: COSTES OPERATIVOS
A11: Fuel | B11: 0 | C11: 0 | D11: 0 | E11: 0 | F11: 0 | G11: -35899290 | H11: 0 | I11: 0 | J11: 0 | K11: 0 | L11: 0 | M11: 0 | N11: =SUM(B11:M11)
A12: Crew | B12: 0 | C12: 0 | D12: 0 | E12: 0 | F12: 0 | G12: -8414640.6 | H12: 0 | I12: 0 | J12: 0 | K12: 0 | L12: 0 | M12: 0 | N12: =SUM(B12:M12)
A13: Maintenance | B13: 0 | C13: 0 | D13: 0 | E13: 0 | F13: 0 | G13: -5710849.6 | H13: 0 | I13: 0 | J13: 0 | K13: 0 | L13: 0 | M13: 0 | N13: =SUM(B13:M13)
A14: Airport & Navigation | B14: 0 | C14: 0 | D14: 0 | E14: 0 | F14: 0 | G14: -8030910.4 | H14: 0 | I14: 0 | J14: 0 | K14: 0 | L14: 0 | M14: 0 | N14: =SUM(B14:M14)
A15: Handling | B15: 0 | C15: 0 | D15: 0 | E15: 0 | F15: 0 | G15: -7369747.5 | H15: 0 | I15: 0 | J15: 0 | K15: 0 | L15: 0 | M15: 0 | N15: =SUM(B15:M15)
A16: Sales & Distribution | B16: 0 | C16: 0 | D16: 0 | E16: 0 | F16: 0 | G16: -4848405.2 | H16: 0 | I16: 0 | J16: 0 | K16: 0 | L16: 0 | M16: 0 | N16: =SUM(B16:M16)
A17: G&A | B17: 0 | C17: 0 | D17: 0 | E17: 0 | F17: 0 | G17: -8119261.8 | H17: 0 | I17: 0 | J17: 0 | K17: 0 | L17: 0 | M17: 0 | N17: =SUM(B17:M17)
A18: EBITDA | B18: =B9+SUM(B11:B17) | C18: =C9+SUM(C11:C17) | D18: =D9+SUM(D11:D17) | E18: =E9+SUM(E11:E17) | F18: =F9+SUM(F11:F17) | G18: =G9+SUM(G11:G17) | H18: =H9+SUM(H11:H17) | I18: =I9+SUM(I11:I17) | ... M18: =M9+SUM(M11:M17) | N18: =SUM(B18:M18)
A19: RESULTADO FINANCIERO
A20: Interest | B20: 0 | C20: 0 | D20: 0 | E20: 0 | F20: 0 | G20: -33333.3 | H20: 0 | I20: 0 | J20: 0 | K20: 0 | L20: 0 | M20: 0 | N20: =SUM(B20:M20)
A21: EBT / RESULTADO NETO | B21: =B18+SUM(B20:B20) | C21: =C18+SUM(C20:C20) | D21: =D18+SUM(D20:D20) | E21: =E18+SUM(E20:E20) | F21: =F18+SUM(F20:F20) | G21: =G18+SUM(G20:G20) | H21: =H18+SUM(H20:H20) | I21: =I18+SUM(I20:I20) | ... M21: =M18+SUM(M20:M20) | N21: =SUM(B21:M21)

Sheet Actual (ST)
A1: ACTUAL (ST) 2026 — P&L mensual (€) · Junio cerrado
A3: Concepto | B3: Ene | C3: Feb | D3: Mar | E3: Abr | F3: May | G3: Jun | H3: Jul | I3: Ago | J3: Sep | K3: Oct | L3: Nov | M3: Dic | N3: FY Total
A4: INGRESOS
A5: Passenger Revenue | B5: 0 | C5: 0 | D5: 0 | E5: 0 | F5: 0 | G5: 51819512 | H5: 0 | I5: 0 | J5: 0 | K5: 0 | L5: 0 | M5: 0 | N5: =SUM(B5:M5)
A6: Shuttle | B6: 0 | C6: 0 | D6: 0 | E6: 0 | F6: 0 | G6: 792087.6 | H6: 0 | I6: 0 | J6: 0 | K6: 0 | L6: 0 | M6: 0 | N6: =SUM(B6:M6)
A7: Charter | B7: 0 | C7: 0 | D7: 0 | E7: 0 | F7: 0 | G7: -14584.4 | H7: 0 | I7: 0 | J7: 0 | K7: 0 | L7: 0 | M7: 0 | N7: =SUM(B7:M7)
A8: Ancillary Revenue | B8: 0 | C8: 0 | D8: 0 | E8: 0 | F8: 0 | G8: 31198002 | H8: 0 | I8: 0 | J8: 0 | K8: 0 | L8: 0 | M8: 0 | N8: =SUM(B8:M8)
A9: Total Revenue | B9: =SUM(B5:B8) | C9: =SUM(C5:C8) | D9: =SUM(D5:D8) | E9: =SUM(E5:E8) | F9: =SUM(F5:F8) | G9: =SUM(G5:G8) | H9: =SUM(H5:H8) | I9: =SUM(I5:I8) | ... M9: =SUM(M5:M8) | N9: =SUM(B9:M9)
A10: COSTES OPERATIVOS
A11: Fuel | B11: 0 | C11: 0 | D11: 0 | E11: 0 | F11: 0 | G11: -41526566 | H11: 0 | I11: 0 | J11: 0 | K11: 0 | L11: 0 | M11: 0 | N11: =SUM(B11:M11)
A12: Crew | B12: 0 | C12: 0 | D12: 0 | E12: 0 | F12: 0 | G12: -8174673.4 | H12: 0 | I12: 0 | J12: 0 | K12: 0 | L12: 0 | M12: 0 | N12: =SUM(B12:M12)
A13: Maintenance | B13: 0 | C13: 0 | D13: 0 | E13: 0 | F13: 0 | G13: -6520046.3 | H13: 0 | I13: 0 | J13: 0 | K13: 0 | L13: 0 | M13: 0 | N13: =SUM(B13:M13)
A14: Airport & Navigation | B14: 0 | C14: 0 | D14: 0 | E14: 0 | F14: 0 | G14: -7038581.8 | H14: 0 | I14: 0 | J14: 0 | K14: 0 | L14: 0 | M14: 0 | N14: =SUM(B14:M14)
A15: Handling | B15: 0 | C15: 0 | D15: 0 | E15: 0 | F15: 0 | G15: -6884768.9 | H15: 0 | I15: 0 | J15: 0 | K15: 0 | L15: 0 | M15: 0 | N15: =SUM(B15:M15)
A16: Sales & Distribution | B16: 0 | C16: 0 | D16: 0 | E16: 0 | F16: 0 | G16: -4704608.5 | H16: 0 | I16: 0 | J16: 0 | K16: 0 | L16: 0 | M16: 0 | N16: =SUM(B16:M16)
A17: G&A | B17: 0 | C17: 0 | D17: 0 | E17: 0 | F17: 0 | G17: -8225842.4 | H17: 0 | I17: 0 | J17: 0 | K17: 0 | L17: 0 | M17: 0 | N17: =SUM(B17:M17)
A18: EBITDA | B18: =B9+SUM(B11:B17) | C18: =C9+SUM(C11:C17) | D18: =D9+SUM(D11:D17) | E18: =E9+SUM(E11:E17) | F18: =F9+SUM(F11:F17) | G18: =G9+SUM(G11:G17) | H18: =H9+SUM(H11:H17) | I18: =I9+SUM(I11:I17) | ... M18: =M9+SUM(M11:M17) | N18: =SUM(B18:M18)
A19: RESULTADO FINANCIERO
A20: Interest | B20: 0 | C20: 0 | D20: 0 | E20: 0 | F20: 0 | G20: 0 | H20: 0 | I20: 0 | J20: 0 | K20: 0 | L20: 0 | M20: 0 | N20: =SUM(B20:M20)
A21: EBT / RESULTADO NETO | B21: =B18+SUM(B20:B20) | C21: =C18+SUM(C20:C20) | D21: =D18+SUM(D20:D20) | E21: =E18+SUM(E20:E20) | F21: =F18+SUM(F20:F20) | G21: =G18+SUM(G20:G20) | H21: =H18+SUM(H20:H20) | I21: =I18+SUM(I20:I20) | ... M21: =M18+SUM(M20:M20) | N21: =SUM(B21:M21)

Sheet Variaciones
A1: VARIACIONES (Actual − Budget) €
A3: Concepto | B3: Ene | C3: Feb | D3: Mar | E3: Abr | F3: May | G3: Jun | H3: Jul | I3: Ago | J3: Sep | K3: Oct | L3: Nov | M3: Dic | N3: FY Total
A4: INGRESOS
A5: Passenger Revenue | B5: ='Actual (ST)'!B5-Budget!B5 | C5: ='Actual (ST)'!C5-Budget!C5 | D5: ='Actual (ST)'!D5-Budget!D5 | E5: ='Actual (ST)'!E5-Budget!E5 | F5: ='Actual (ST)'!F5-Budget!F5 | G5: ='Actual (ST)'!G5-Budget!G5 | H5: ='Actual (ST)'!H5-Budget!H5 | I5: ='Actual (ST)'!I5-Budget!I5 | ... N5: ='Actual (ST)'!N5-Budget!N5
A6: Shuttle | B6: ='Actual (ST)'!B6-Budget!B6 | C6: ='Actual (ST)'!C6-Budget!C6 | D6: ='Actual (ST)'!D6-Budget!D6 | E6: ='Actual (ST)'!E6-Budget!E6 | F6: ='Actual (ST)'!F6-Budget!F6 | G6: ='Actual (ST)'!G6-Budget!G6 | H6: ='Actual (ST)'!H6-Budget!H6 | I6: ='Actual (ST)'!I6-Budget!I6 | ... N6: ='Actual (ST)'!N6-Budget!N6
A7: Charter | B7: ='Actual (ST)'!B7-Budget!B7 | C7: ='Actual (ST)'!C7-Budget!C7 | D7: ='Actual (ST)'!D7-Budget!D7 | E7: ='Actual (ST)'!E7-Budget!E7 | F7: ='Actual (ST)'!F7-Budget!F7 | G7: ='Actual (ST)'!G7-Budget!G7 | H7: ='Actual (ST)'!H7-Budget!H7 | I7: ='Actual (ST)'!I7-Budget!I7 | ... N7: ='Actual (ST)'!N7-Budget!N7
A8: Ancillary Revenue | B8: ='Actual (ST)'!B8-Budget!B8 | C8: ='Actual (ST)'!C8-Budget!C8 | D8: ='Actual (ST)'!D8-Budget!D8 | E8: ='Actual (ST)'!E8-Budget!E8 | F8: ='Actual (ST)'!F8-Budget!F8 | G8: ='Actual (ST)'!G8-Budget!G8 | H8: ='Actual (ST)'!H8-Budget!H8 | I8: ='Actual (ST)'!I8-Budget!I8 | ... N8: ='Actual (ST)'!N8-Budget!N8
A9: Total Revenue | B9: ='Actual (ST)'!B9-Budget!B9 | C9: ='Actual (ST)'!C9-Budget!C9 | D9: ='Actual (ST)'!D9-Budget!D9 | E9: ='Actual (ST)'!E9-Budget!E9 | F9: ='Actual (ST)'!F9-Budget!F9 | G9: ='Actual (ST)'!G9-Budget!G9 | H9: ='Actual (ST)'!H9-Budget!H9 | I9: ='Actual (ST)'!I9-Budget!I9 | ... N9: ='Actual (ST)'!N9-Budget!N9
A10: COSTES OPERATIVOS
A11: Fuel | B11: ='Actual (ST)'!B11-Budget!B11 | C11: ='Actual (ST)'!C11-Budget!C11 | D11: ='Actual (ST)'!D11-Budget!D11 | E11: ='Actual (ST)'!E11-Budget!E11 | F11: ='Actual (ST)'!F11-Budget!F11 | G11: ='Actual (ST)'!G11-Budget!G11 | H11: ='Actual (ST)'!H11-Budget!H11 | I11: ='Actual (ST)'!I11-Budget!I11 | ... N11: ='Actual (ST)'!N11-Budget!N11
A12: Crew | B12: ='Actual (ST)'!B12-Budget!B12 | C12: ='Actual (ST)'!C12-Budget!C12 | D12: ='Actual (ST)'!D12-Budget!D12 | E12: ='Actual (ST)'!E12-Budget!E12 | F12: ='Actual (ST)'!F12-Budget!F12 | G12: ='Actual (ST)'!G12-Budget!G12 | H12: ='Actual (ST)'!H12-Budget!H12 | I12: ='Actual (ST)'!I12-Budget!I12 | ... N12: ='Actual (ST)'!N12-Budget!N12
A13: Maintenance | B13: ='Actual (ST)'!B13-Budget!B13 | C13: ='Actual (ST)'!C13-Budget!C13 | D13: ='Actual (ST)'!D13-Budget!D13 | E13: ='Actual (ST)'!E13-Budget!E13 | F13: ='Actual (ST)'!F13-Budget!F13 | G13: ='Actual (ST)'!G13-Budget!G13 | H13: ='Actual (ST)'!H13-Budget!H13 | I13: ='Actual (ST)'!I13-Budget!I13 | ... N13: ='Actual (ST)'!N13-Budget!N13
A14: Airport & Navigation | B14: ='Actual (ST)'!B14-Budget!B14 | C14: ='Actual (ST)'!C14-Budget!C14 | D14: ='Actual (ST)'!D14-Budget!D14 | E14: ='Actual (ST)'!E14-Budget!E14 | F14: ='Actual (ST)'!F14-Budget!F14 | G14: ='Actual (ST)'!G14-Budget!G14 | H14: ='Actual (ST)'!H14-Budget!H14 | I14: ='Actual (ST)'!I14-Budget!I14 | ... N14: ='Actual (ST)'!N14-Budget!N14
A15: Handling | B15: ='Actual (ST)'!B15-Budget!B15 | C15: ='Actual (ST)'!C15-Budget!C15 | D15: ='Actual (ST)'!D15-Budget!D15 | E15: ='Actual (ST)'!E15-Budget!E15 | F15: ='Actual (ST)'!F15-Budget!F15 | G15: ='Actual (ST)'!G15-Budget!G15 | H15: ='Actual (ST)'!H15-Budget!H15 | I15: ='Actual (ST)'!I15-Budget!I15 | ... N15: ='Actual (ST)'!N15-Budget!N15
A16: Sales & Distribution | B16: ='Actual (ST)'!B16-Budget!B16 | C16: ='Actual (ST)'!C16-Budget!C16 | D16: ='Actual (ST)'!D16-Budget!D16 | E16: ='Actual (ST)'!E16-Budget!E16 | F16: ='Actual (ST)'!F16-Budget!F16 | G16: ='Actual (ST)'!G16-Budget!G16 | H16: ='Actual (ST)'!H16-Budget!H16 | I16: ='Actual (ST)'!I16-Budget!I16 | ... N16: ='Actual (ST)'!N16-Budget!N16
A17: G&A | B17: ='Actual (ST)'!B17-Budget!B17 | C17: ='Actual (ST)'!C17-Budget!C17 | D17: ='Actual (ST)'!D17-Budget!D17 | E17: ='Actual (ST)'!E17-Budget!E17 | F17: ='Actual (ST)'!F17-Budget!F17 | G17: ='Actual (ST)'!G17-Budget!G17 | H17: ='Actual (ST)'!H17-Budget!H17 | I17: ='Actual (ST)'!I17-Budget!I17 | ... N17: ='Actual (ST)'!N17-Budget!N17
A18: EBITDA | B18: ='Actual (ST)'!B18-Budget!B18 | C18: ='Actual (ST)'!C18-Budget!C18 | D18: ='Actual (ST)'!D18-Budget!D18 | E18: ='Actual (ST)'!E18-Budget!E18 | F18: ='Actual (ST)'!F18-Budget!F18 | G18: ='Actual (ST)'!G18-Budget!G18 | H18: ='Actual (ST)'!H18-Budget!H18 | I18: ='Actual (ST)'!I18-Budget!I18 | ... N18: ='Actual (ST)'!N18-Budget!N18
A19: RESULTADO FINANCIERO
A20: Interest | B20: ='Actual (ST)'!B20-Budget!B20 | C20: ='Actual (ST)'!C20-Budget!C20 | D20: ='Actual (ST)'!D20-Budget!D20 | E20: ='Actual (ST)'!E20-Budget!E20 | F20: ='Actual (ST)'!F20-Budget!F20 | G20: ='Actual (ST)'!G20-Budget!G20 | H20: ='Actual (ST)'!H20-Budget!H20 | I20: ='Actual (ST)'!I20-Budget!I20 | ... N20: ='Actual (ST)'!N20-Budget!N20
A21: EBT / RESULTADO NETO | B21: ='Actual (ST)'!B21-Budget!B21 | C21: ='Actual (ST)'!C21-Budget!C21 | D21: ='Actual (ST)'!D21-Budget!D21 | E21: ='Actual (ST)'!E21-Budget!E21 | F21: ='Actual (ST)'!F21-Budget!F21 | G21: ='Actual (ST)'!G21-Budget!G21 | H21: ='Actual (ST)'!H21-Budget!H21 | I21: ='Actual (ST)'!I21-Budget!I21 | ... N21: ='Actual (ST)'!N21-Budget!N21

Sheet Variaciones %
A1: VARIACIONES % (vs Budget)
A3: Concepto | B3: Ene | C3: Feb | D3: Mar | E3: Abr | F3: May | G3: Jun | H3: Jul | I3: Ago | J3: Sep | K3: Oct | L3: Nov | M3: Dic | N3: FY Total
A4: INGRESOS
A5: Passenger Revenue | B5: =IF(Budget!B5=0,"",('Actual (ST)'!B5-Budget!B5)/ABS(Budget!B5)) | C5: =IF(Budget!C5=0,"",('Actual (ST)'!C5-Budget!C5)/ABS(Budget!C5)) | D5: =IF(Budget!D5=0,"",('Actual (ST)'!D5-Budget!D5)/ABS(Budget!D5)) | E5: =IF(Budget!E5=0,"",('Actual (ST)'!E5-Budget!E5)/ABS(Budget!E5)) | F5: =IF(Budget!F5=0,"",('Actual (ST)'!F5-Budget!F5)/ABS(Budget!F5)) | G5: =IF(Budget!G5=0,"",('Actual (ST)'!G5-Budget!G5)/ABS(Budget!G5)) | H5: =IF(Budget!H5=0,"",('Actual (ST)'!H5-Budget!H5)/ABS(Budget!H5)) | I5: =IF(Budget!I5=0,"",('Actual (ST)'!I5-Budget!I5)/ABS(Budget!I5)) | ... N5: =IF(Budget!N5=0,"",('Actual (ST)'!N5-Budget!N5)/ABS(Budget!N5))
A6: Shuttle | B6: =IF(Budget!B6=0,"",('Actual (ST)'!B6-Budget!B6)/ABS(Budget!B6)) | C6: =IF(Budget!C6=0,"",('Actual (ST)'!C6-Budget!C6)/ABS(Budget!C6)) | D6: =IF(Budget!D6=0,"",('Actual (ST)'!D6-Budget!D6)/ABS(Budget!D6)) | E6: =IF(Budget!E6=0,"",('Actual (ST)'!E6-Budget!E6)/ABS(Budget!E6)) | F6: =IF(Budget!F6=0,"",('Actual (ST)'!F6-Budget!F6)/ABS(Budget!F6)) | G6: =IF(Budget!G6=0,"",('Actual (ST)'!G6-Budget!G6)/ABS(Budget!G6)) | H6: =IF(Budget!H6=0,"",('Actual (ST)'!H6-Budget!H6)/ABS(Budget!H6)) | I6: =IF(Budget!I6=0,"",('Actual (ST)'!I6-Budget!I6)/ABS(Budget!I6)) | ... N6: =IF(Budget!N6=0,"",('Actual (ST)'!N6-Budget!N6)/ABS(Budget!N6))
A7: Charter | B7: =IF(Budget!B7=0,"",('Actual (ST)'!B7-Budget!B7)/ABS(Budget!B7)) | C7: =IF(Budget!C7=0,"",('Actual (ST)'!C7-Budget!C7)/ABS(Budget!C7)) | D7: =IF(Budget!D7=0,"",('Actual (ST)'!D7-Budget!D7)/ABS(Budget!D7)) | E7: =IF(Budget!E7=0,"",('Actual (ST)'!E7-Budget!E7)/ABS(Budget!E7)) | F7: =IF(Budget!F7=0,"",('Actual (ST)'!F7-Budget!F7)/ABS(Budget!F7)) | G7: =IF(Budget!G7=0,"",('Actual (ST)'!G7-Budget!G7)/ABS(Budget!G7)) | H7: =IF(Budget!H7=0,"",('Actual (ST)'!H7-Budget!H7)/ABS(Budget!H7)) | I7: =IF(Budget!I7=0,"",('Actual (ST)'!I7-Budget!I7)/ABS(Budget!I7)) | ... N7: =IF(Budget!N7=0,"",('Actual (ST)'!N7-Budget!N7)/ABS(Budget!N7))
A8: Ancillary Revenue | B8: =IF(Budget!B8=0,"",('Actual (ST)'!B8-Budget!B8)/ABS(Budget!B8)) | C8: =IF(Budget!C8=0,"",('Actual (ST)'!C8-Budget!C8)/ABS(Budget!C8)) | D8: =IF(Budget!D8=0,"",('Actual (ST)'!D8-Budget!D8)/ABS(Budget!D8)) | E8: =IF(Budget!E8=0,"",('Actual (ST)'!E8-Budget!E8)/ABS(Budget!E8)) | F8: =IF(Budget!F8=0,"",('Actual (ST)'!F8-Budget!F8)/ABS(Budget!F8)) | G8: =IF(Budget!G8=0,"",('Actual (ST)'!G8-Budget!G8)/ABS(Budget!G8)) | H8: =IF(Budget!H8=0,"",('Actual (ST)'!H8-Budget!H8)/ABS(Budget!H8)) | I8: =IF(Budget!I8=0,"",('Actual (ST)'!I8-Budget!I8)/ABS(Budget!I8)) | ... N8: =IF(Budget!N8=0,"",('Actual (ST)'!N8-Budget!N8)/ABS(Budget!N8))
A9: Total Revenue | B9: =IF(Budget!B9=0,"",('Actual (ST)'!B9-Budget!B9)/ABS(Budget!B9)) | C9: =IF(Budget!C9=0,"",('Actual (ST)'!C9-Budget!C9)/ABS(Budget!C9)) | D9: =IF(Budget!D9=0,"",('Actual (ST)'!D9-Budget!D9)/ABS(Budget!D9)) | E9: =IF(Budget!E9=0,"",('Actual (ST)'!E9-Budget!E9)/ABS(Budget!E9)) | F9: =IF(Budget!F9=0,"",('Actual (ST)'!F9-Budget!F9)/ABS(Budget!F9)) | G9: =IF(Budget!G9=0,"",('Actual (ST)'!G9-Budget!G9)/ABS(Budget!G9)) | H9: =IF(Budget!H9=0,"",('Actual (ST)'!H9-Budget!H9)/ABS(Budget!H9)) | I9: =IF(Budget!I9=0,"",('Actual (ST)'!I9-Budget!I9)/ABS(Budget!I9)) | ... N9: =IF(Budget!N9=0,"",('Actual (ST)'!N9-Budget!N9)/ABS(Budget!N9))
A10: COSTES OPERATIVOS
A11: Fuel | B11: =IF(Budget!B11=0,"",('Actual (ST)'!B11-Budget!B11)/ABS(Budget!B11)) | C11: =IF(Budget!C11=0,"",('Actual (ST)'!C11-Budget!C11)/ABS(Budget!C11)) | D11: =IF(Budget!D11=0,"",('Actual (ST)'!D11-Budget!D11)/ABS(Budget!D11)) | E11: =IF(Budget!E11=0,"",('Actual (ST)'!E11-Budget!E11)/ABS(Budget!E11)) | F11: =IF(Budget!F11=0,"",('Actual (ST)'!F11-Budget!F11)/ABS(Budget!F11)) | G11: =IF(Budget!G11=0,"",('Actual (ST)'!G11-Budget!G11)/ABS(Budget!G11)) | H11: =IF(Budget!H11=0,"",('Actual (ST)'!H11-Budget!H11)/ABS(Budget!H11)) | I11: =IF(Budget!I11=0,"",('Actual (ST)'!I11-Budget!I11)/ABS(Budget!I11)) | ... N11: =IF(Budget!N11=0,"",('Actual (ST)'!N11-Budget!N11)/ABS(Budget!N11))
A12: Crew | B12: =IF(Budget!B12=0,"",('Actual (ST)'!B12-Budget!B12)/ABS(Budget!B12)) | C12: =IF(Budget!C12=0,"",('Actual (ST)'!C12-Budget!C12)/ABS(Budget!C12)) | D12: =IF(Budget!D12=0,"",('Actual (ST)'!D12-Budget!D12)/ABS(Budget!D12)) | E12: =IF(Budget!E12=0,"",('Actual (ST)'!E12-Budget!E12)/ABS(Budget!E12)) | F12: =IF(Budget!F12=0,"",('Actual (ST)'!F12-Budget!F12)/ABS(Budget!F12)) | G12: =IF(Budget!G12=0,"",('Actual (ST)'!G12-Budget!G12)/ABS(Budget!G12)) | H12: =IF(Budget!H12=0,"",('Actual (ST)'!H12-Budget!H12)/ABS(Budget!H12)) | I12: =IF(Budget!I12=0,"",('Actual (ST)'!I12-Budget!I12)/ABS(Budget!I12)) | ... N12: =IF(Budget!N12=0,"",('Actual (ST)'!N12-Budget!N12)/ABS(Budget!N12))
A13: Maintenance | B13: =IF(Budget!B13=0,"",('Actual (ST)'!B13-Budget!B13)/ABS(Budget!B13)) | C13: =IF(Budget!C13=0,"",('Actual (ST)'!C13-Budget!C13)/ABS(Budget!C13)) | D13: =IF(Budget!D13=0,"",('Actual (ST)'!D13-Budget!D13)/ABS(Budget!D13)) | E13: =IF(Budget!E13=0,"",('Actual (ST)'!E13-Budget!E13)/ABS(Budget!E13)) | F13: =IF(Budget!F13=0,"",('Actual (ST)'!F13-Budget!F13)/ABS(Budget!F13)) | G13: =IF(Budget!G13=0,"",('Actual (ST)'!G13-Budget!G13)/ABS(Budget!G13)) | H13: =IF(Budget!H13=0,"",('Actual (ST)'!H13-Budget!H13)/ABS(Budget!H13)) | I13: =IF(Budget!I13=0,"",('Actual (ST)'!I13-Budget!I13)/ABS(Budget!I13)) | ... N13: =IF(Budget!N13=0,"",('Actual (ST)'!N13-Budget!N13)/ABS(Budget!N13))
A14: Airport & Navigation | B14: =IF(Budget!B14=0,"",('Actual (ST)'!B14-Budget!B14)/ABS(Budget!B14)) | C14: =IF(Budget!C14=0,"",('Actual (ST)'!C14-Budget!C14)/ABS(Budget!C14)) | D14: =IF(Budget!D14=0,"",('Actual (ST)'!D14-Budget!D14)/ABS(Budget!D14)) | E14: =IF(Budget!E14=0,"",('Actual (ST)'!E14-Budget!E14)/ABS(Budget!E14)) | F14: =IF(Budget!F14=0,"",('Actual (ST)'!F14-Budget!F14)/ABS(Budget!F14)) | G14: =IF(Budget!G14=0,"",('Actual (ST)'!G14-Budget!G14)/ABS(Budget!G14)) | H14: =IF(Budget!H14=0,"",('Actual (ST)'!H14-Budget!H14)/ABS(Budget!H14)) | I14: =IF(Budget!I14=0,"",('Actual (ST)'!I14-Budget!I14)/ABS(Budget!I14)) | ... N14: =IF(Budget!N14=0,"",('Actual (ST)'!N14-Budget!N14)/ABS(Budget!N14))
A15: Handling | B15: =IF(Budget!B15=0,"",('Actual (ST)'!B15-Budget!B15)/ABS(Budget!B15)) | C15: =IF(Budget!C15=0,"",('Actual (ST)'!C15-Budget!C15)/ABS(Budget!C15)) | D15: =IF(Budget!D15=0,"",('Actual (ST)'!D15-Budget!D15)/ABS(Budget!D15)) | E15: =IF(Budget!E15=0,"",('Actual (ST)'!E15-Budget!E15)/ABS(Budget!E15)) | F15: =IF(Budget!F15=0,"",('Actual (ST)'!F15-Budget!F15)/ABS(Budget!F15)) | G15: =IF(Budget!G15=0,"",('Actual (ST)'!G15-Budget!G15)/ABS(Budget!G15)) | H15: =IF(Budget!H15=0,"",('Actual (ST)'!H15-Budget!H15)/ABS(Budget!H15)) | I15: =IF(Budget!I15=0,"",('Actual (ST)'!I15-Budget!I15)/ABS(Budget!I15)) | ... N15: =IF(Budget!N15=0,"",('Actual (ST)'!N15-Budget!N15)/ABS(Budget!N15))
A16: Sales & Distribution | B16: =IF(Budget!B16=0,"",('Actual (ST)'!B16-Budget!B16)/ABS(Budget!B16)) | C16: =IF(Budget!C16=0,"",('Actual (ST)'!C16-Budget!C16)/ABS(Budget!C16)) | D16: =IF(Budget!D16=0,"",('Actual (ST)'!D16-Budget!D16)/ABS(Budget!D16)) | E16: =IF(Budget!E16=0,"",('Actual (ST)'!E16-Budget!E16)/ABS(Budget!E16)) | F16: =IF(Budget!F16=0,"",('Actual (ST)'!F16-Budget!F16)/ABS(Budget!F16)) | G16: =IF(Budget!G16=0,"",('Actual (ST)'!G16-Budget!G16)/ABS(Budget!G16)) | H16: =IF(Budget!H16=0,"",('Actual (ST)'!H16-Budget!H16)/ABS(Budget!H16)) | I16: =IF(Budget!I16=0,"",('Actual (ST)'!I16-Budget!I16)/ABS(Budget!I16)) | ... N16: =IF(Budget!N16=0,"",('Actual (ST)'!N16-Budget!N16)/ABS(Budget!N16))
A17: G&A | B17: =IF(Budget!B17=0,"",('Actual (ST)'!B17-Budget!B17)/ABS(Budget!B17)) | C17: =IF(Budget!C17=0,"",('Actual (ST)'!C17-Budget!C17)/ABS(Budget!C17)) | D17: =IF(Budget!D17=0,"",('Actual (ST)'!D17-Budget!D17)/ABS(Budget!D17)) | E17: =IF(Budget!E17=0,"",('Actual (ST)'!E17-Budget!E17)/ABS(Budget!E17)) | F17: =IF(Budget!F17=0,"",('Actual (ST)'!F17-Budget!F17)/ABS(Budget!F17)) | G17: =IF(Budget!G17=0,"",('Actual (ST)'!G17-Budget!G17)/ABS(Budget!G17)) | H17: =IF(Budget!H17=0,"",('Actual (ST)'!H17-Budget!H17)/ABS(Budget!H17)) | I17: =IF(Budget!I17=0,"",('Actual (ST)'!I17-Budget!I17)/ABS(Budget!I17)) | ... N17: =IF(Budget!N17=0,"",('Actual (ST)'!N17-Budget!N17)/ABS(Budget!N17))
A18: EBITDA | B18: =IF(Budget!B18=0,"",('Actual (ST)'!B18-Budget!B18)/ABS(Budget!B18)) | C18: =IF(Budget!C18=0,"",('Actual (ST)'!C18-Budget!C18)/ABS(Budget!C18)) | D18: =IF(Budget!D18=0,"",('Actual (ST)'!D18-Budget!D18)/ABS(Budget!D18)) | E18: =IF(Budget!E18=0,"",('Actual (ST)'!E18-Budget!E18)/ABS(Budget!E18)) | F18: =IF(Budget!F18=0,"",('Actual (ST)'!F18-Budget!F18)/ABS(Budget!F18)) | G18: =IF(Budget!G18=0,"",('Actual (ST)'!G18-Budget!G18)/ABS(Budget!G18)) | H18: =IF(Budget!H18=0,"",('Actual (ST)'!H18-Budget!H18)/ABS(Budget!H18)) | I18: =IF(Budget!I18=0,"",('Actual (ST)'!I18-Budget!I18)/ABS(Budget!I18)) | ... N18: =IF(Budget!N18=0,"",('Actual (ST)'!N18-Budget!N18)/ABS(Budget!N18))
A19: RESULTADO FINANCIERO
A20: Interest | B20: =IF(Budget!B20=0,"",('Actual (ST)'!B20-Budget!B20)/ABS(Budget!B20)) | C20: =IF(Budget!C20=0,"",('Actual (ST)'!C20-Budget!C20)/ABS(Budget!C20)) | D20: =IF(Budget!D20=0,"",('Actual (ST)'!D20-Budget!D20)/ABS(Budget!D20)) | E20: =IF(Budget!E20=0,"",('Actual (ST)'!E20-Budget!E20)/ABS(Budget!E20)) | F20: =IF(Budget!F20=0,"",('Actual (ST)'!F20-Budget!F20)/ABS(Budget!F20)) | G20: =IF(Budget!G20=0,"",('Actual (ST)'!G20-Budget!G20)/ABS(Budget!G20)) | H20: =IF(Budget!H20=0,"",('Actual (ST)'!H20-Budget!H20)/ABS(Budget!H20)) | I20: =IF(Budget!I20=0,"",('Actual (ST)'!I20-Budget!I20)/ABS(Budget!I20)) | ... N20: =IF(Budget!N20=0,"",('Actual (ST)'!N20-Budget!N20)/ABS(Budget!N20))
A21: EBT / RESULTADO NETO | B21: =IF(Budget!B21=0,"",('Actual (ST)'!B21-Budget!B21)/ABS(Budget!B21)) | C21: =IF(Budget!C21=0,"",('Actual (ST)'!C21-Budget!C21)/ABS(Budget!C21)) | D21: =IF(Budget!D21=0,"",('Actual (ST)'!D21-Budget!D21)/ABS(Budget!D21)) | E21: =IF(Budget!E21=0,"",('Actual (ST)'!E21-Budget!E21)/ABS(Budget!E21)) | F21: =IF(Budget!F21=0,"",('Actual (ST)'!F21-Budget!F21)/ABS(Budget!F21)) | G21: =IF(Budget!G21=0,"",('Actual (ST)'!G21-Budget!G21)/ABS(Budget!G21)) | H21: =IF(Budget!H21=0,"",('Actual (ST)'!H21-Budget!H21)/ABS(Budget!H21)) | I21: =IF(Budget!I21=0,"",('Actual (ST)'!I21-Budget!I21)/ABS(Budget!I21)) | ... N21: =IF(Budget!N21=0,"",('Actual (ST)'!N21-Budget!N21)/ABS(Budget!N21))

Sheet Dashboard
A1: DASHBOARD — Junio 2026 (Budget vs Actual)
A3: Concepto | B3: Budget | C3: Actual | D3: Variación | E3: Var %
A4: Total Revenue | B4: =Budget!G9 | C4: ='Actual (ST)'!G9 | D4: =C4-B4 | E4: =IF(B4=0,"",D4/ABS(B4))
A5: Fuel | B5: =Budget!G11 | C5: ='Actual (ST)'!G11 | D5: =C5-B5 | E5: =IF(B5=0,"",D5/ABS(B5))
A6: Crew | B6: =Budget!G12 | C6: ='Actual (ST)'!G12 | D6: =C6-B6 | E6: =IF(B6=0,"",D6/ABS(B6))
A7: Maintenance | B7: =Budget!G13 | C7: ='Actual (ST)'!G13 | D7: =C7-B7 | E7: =IF(B7=0,"",D7/ABS(B7))
A8: Airport & Navigation | B8: =Budget!G14 | C8: ='Actual (ST)'!G14 | D8: =C8-B8 | E8: =IF(B8=0,"",D8/ABS(B8))
A9: Handling | B9: =Budget!G15 | C9: ='Actual (ST)'!G15 | D9: =C9-B9 | E9: =IF(B9=0,"",D9/ABS(B9))
A10: Sales & Distribution | B10: =Budget!G16 | C10: ='Actual (ST)'!G16 | D10: =C10-B10 | E10: =IF(B10=0,"",D10/ABS(B10))
A11: G&A | B11: =Budget!G17 | C11: ='Actual (ST)'!G17 | D11: =C11-B11 | E11: =IF(B11=0,"",D11/ABS(B11))
A12: EBITDA | B12: =Budget!G18 | C12: ='Actual (ST)'!G18 | D12: =C12-B12 | E12: =IF(B12=0,"",D12/ABS(B12))
A13: EBT / Neto | B13: =Budget!G21 | C13: ='Actual (ST)'!G21 | D13: =C13-B13 | E13: =IF(B13=0,"",D13/ABS(B13))

Sheet Puente PL-Caja
A1: PUENTE P&L → CAJA (€k) — parte del EBITDA y baja a caja vía circulante
A3: Concepto | B3: Ene | C3: Feb | D3: Mar | E3: Abr | F3: May | G3: Jun | H3: Jul | I3: Ago | J3: Sep | K3: Oct | L3: Nov | M3: Dic
A4: SALDOS DE BALANCE (€k) · pega aquí del ST cada mes
A5: Trade & Other Receivables (saldo) | F5: 62049 | G5: 64297
A6: Trade Payables & Accruals c/p (saldo) | F6: 278212 | G6: 282393
A7: Accruals l/p (saldo) | F7: 17873 | G7: 17789
A8: Deferred Income - air traffic liab. (saldo) | F8: 195738 | G8: 190268
A9: Cash & Cash Equivalents (saldo) | F9: 68882 | G9: 54179
A11: PUENTE P&L → CAJA (€k)
A12: EBITDA (desde P&L Actual) | B12: ='Actual (ST)'!B18/1000 | C12: ='Actual (ST)'!C18/1000 | D12: ='Actual (ST)'!D18/1000 | E12: ='Actual (ST)'!E18/1000 | F12: ='Actual (ST)'!F18/1000 | G12: ='Actual (ST)'!G18/1000 | H12: ='Actual (ST)'!H18/1000 | I12: ='Actual (ST)'!I18/1000 | ... M12: ='Actual (ST)'!M18/1000
A13: (−) Δ Trade Receivables | C13: =-(C5-B5) | D13: =-(D5-C5) | E13: =-(E5-D5) | F13: =-(F5-E5) | G13: =-(G5-F5) | H13: =-(H5-G5) | I13: =-(I5-H5) | J13: =-(J5-I5) | ... M13: =-(M5-L5)
A14: (+) Δ Trade Payables & Accruals | C14: =(C6-B6) | D14: =(D6-C6) | E14: =(E6-D6) | F14: =(F6-E6) | G14: =(G6-F6) | H14: =(H6-G6) | I14: =(I6-H6) | J14: =(J6-I6) | ... M14: =(M6-L6)
A15: (+) Δ Accruals l/p | C15: =(C7-B7) | D15: =(D7-C7) | E15: =(E7-D7) | F15: =(F7-E7) | G15: =(G7-F7) | H15: =(H7-G7) | I15: =(I7-H7) | J15: =(J7-I7) | ... M15: =(M7-L7)
A16: (+) Δ Deferred Income | C16: =(C8-B8) | D16: =(D8-C8) | E16: =(E8-D8) | F16: =(F8-E8) | G16: =(G8-F8) | H16: =(H8-G8) | I16: =(I8-H8) | J16: =(J8-I8) | ... M16: =(M8-L8)
A17: =Variación Capital Circulante | C17: =SUM(C13:C16) | D17: =SUM(D13:D16) | E17: =SUM(E13:E16) | F17: =SUM(F13:F16) | G17: =SUM(G13:G16) | H17: =SUM(H13:H16) | I17: =SUM(I13:I16) | J17: =SUM(J13:J16) | ... M17: =SUM(M13:M16)
A18: =CASH FLOW OPERATIVO (EBITDA + circulante) | C18: =C12+C17 | D18: =D12+D17 | E18: =E12+E17 | F18: =F12+F17 | G18: =G12+G17 | H18: =H12+H17 | I18: =I12+I17 | J18: =J12+J17 | ... M18: =M12+M17
A19: Δ Caja real (balance) | C19: =(C9-B9) | D19: =(D9-C9) | E19: =(E9-D9) | F19: =(F9-E9) | G19: =(G9-F9) | H19: =(H9-G9) | I19: =(I9-H9) | J19: =(J9-I9) | ... M19: =(M9-L9)
A20: (=) Otros: financiación, leasing, capex, impuestos, intereses | C20: =C19-C18 | D20: =D19-D18 | E20: =E19-E18 | F20: =F19-F18 | G20: =G19-G18 | H20: =H19-H18 | I20: =I19-I18 | J20: =J19-J18 | ... M20: =M19-M18
A23: CÓMO USARLA: cada mes, pega los 5 saldos de balance del ST en la columna del mes (fila 5-9).
A24: El puente (fila 12-20) se recalcula solo: EBITDA + Δcirculante = Cash Flow Operativo; y concilia con la Δ de caja real.
A25: Signos (efecto en CAJA): activo ↑ = caja ↓ (Receivables). Pasivo ↑ = caja ↑ (Payables, Accruals, Deferred Income).
A26: 'Otros' = todo lo que hay bajo EBITDA y fuera de circulante (deuda, leasing IFRS16, capex, impuestos, intereses).
